{
 "tiles": [
  "[N1, N2, N4, N9, N18, N36, N72, N144, N288, N577]",
  "[N1, N2, N4, N8, N16, N33, N66, N132, N265, N531]",
  "[N1, N2, N5, N10, N21, N42, N85, N171, N343, N686]",
  "[N1, N3, N6, N12, N25, N51, N102, N204, N409, N819]",
  "[N1, N3, N7, N14, N28, N56, N113, N227, N455, N911]",
  "[N1, N2, N4, N9, N18, N36, N73, N146, N292, N584]",
  "[N1, N2, N4, N8, N17, N35, N70, N140, N281, N562]",
  "[N1, N3, N7, N15, N31, N63, N126, N252, N505, N1010]",
  "[N1, N2, N5, N11, N22, N45, N90, N181, N363, N727]",
  "[N1, N3, N6, N12, N25, N51, N103, N206, N413, N827]",
  "[N1, N2, N4, N9, N18, N36, N73, N147, N294, N588]",
  "[N1, N2, N5, N11, N22, N45, N91, N182, N365, N730]",
  "[N1, N2, N4, N9, N18, N36, N72, N144, N289, N578]",
  "[N1, N2, N4, N9, N19, N39, N78, N157, N315, N631]",
  "[N1, N2, N4, N8, N17, N35, N70, N141, N283, N566]",
  "[N1, N3, N6, N12, N24, N48, N96, N192, N384, N769]",
  "[N1, N3, N6, N13, N27, N55, N111, N223, N446, N892]",
  "[N1, N3, N6, N12, N25, N51, N103, N207, N414, N829]",
  "[N1, N2, N5, N11, N22, N44, N89, N179, N359, N718]",
  "[N1, N2, N4, N9, N19, N38, N76, N153, N307, N614]",
  "[N1, N2, N5, N10, N20, N41, N82, N164, N328, N656]",
  "[N1, N3, N7, N14, N29, N58, N117, N234, N469, N939]",
  "[N1, N3, N6, N12, N25, N51, N103, N207, N415, N831]",
  "[N1, N2, N5, N10, N21, N42, N85, N170, N341, N683]",
  "[N1, N2, N4, N8, N16, N33, N66, N132, N264, N528]",
  "[N1, N2, N5, N11, N22, N44, N88, N177, N354, N709]",
  "[N1, N3, N7, N14, N29, N58, N116, N232, N465, N931]",
  "[N1, N3, N6, N12, N24, N48, N96, N193, N386, N772]",
  "[N1, N2, N4, N8, N17, N35, N71, N143, N287, N574]",
  "[N1, N2, N4, N8, N17, N35, N71, N143, N287, N575]",
  "[N1, N2, N4, N9, N19, N39, N79, N159, N318, N636]",
  "[N1, N2, N5, N10, N20, N40, N80, N160, N320, N640]",
  "[N1, N2, N5, N10, N21, N43, N86, N173, N347, N695]",
  "[N1, N3, N6, N12, N25, N50, N100, N201, N402, N804]",
  "[N1, N2, N5, N11, N23, N46, N93, N186, N372, N745]",
  "[N1, N2, N5, N10, N21, N43, N86, N173, N346, N692]",
  "[N1, N2, N5, N11, N22, N45, N90, N181, N362, N725]",
  "[N1, N2, N5, N10, N21, N42, N84, N168, N336, N673]",
  "[N1, N3, N6, N13, N26, N52, N105, N210, N421, N842]",
  "[N1, N3, N6, N12, N24, N49, N98, N197, N394, N788]"
 ],
 "symbols": [
  "[N1 - 8]",
  "[N2 - 36]",
  "[N3 - 21]",
  "[N4 - 0]",
  "[N5 - 38]",
  "[N6 - 44]",
  "[N7 - 48]",
  "[N8 - 17]",
  "[N9 - 12]",
  "[N10 - 41]",
  "[N11 - 11]",
  "[N12 - 29]",
  "[N13 - 8]",
  "[N14 - 3]",
  "[N15 - 26]",
  "[N16 - 7]",
  "[N17 - 33]",
  "[N18 - 50]",
  "[N19 - 30]",
  "[N20 - 9]",
  "[N21 - 16]",
  "[N22 - 50]",
  "[N23 - 26]",
  "[N24 - 43]",
  "[N25 - 23]",
  "[N26 - 38]",
  "[N27 - 13]",
  "[N28 - 32]",
  "[N29 - 0]",
  "[N31 - 1]",
  "[N33 - 26]",
  "[N35 - 39]",
  "[N36 - 7]",
  "[N38 - 12]",
  "[N39 - 6]",
  "[N40 - 26]",
  "[N41 - 46]",
  "[N42 - 26]",
  "[N43 - 8]",
  "[N44 - 7]",
  "[N45 - 45]",
  "[N46 - 14]",
  "[N48 - 42]",
  "[N49 - 12]",
  "[N50 - 17]",
  "[N51 - 0]",
  "[N52 - 0]",
  "[N55 - 25]",
  "[N56 - 32]",
  "[N58 - 21]",
  "[N63 - 29]",
  "[N66 - 19]",
  "[N70 - 15]",
  "[N71 - 20]",
  "[N72 - 18]",
  "[N73 - 21]",
  "[N76 - 28]",
  "[N78 - 32]",
  "[N79 - 19]",
  "[N80 - 20]",
  "[N82 - 42]",
  "[N84 - 29]",
  "[N85 - 6]",
  "[N86 - 34]",
  "[N88 - 17]",
  "[N89 - 22]",
  "[N90 - 22]",
  "[N91 - 49]",
  "[N93 - 11]",
  "[N96 - 18]",
  "[N98 - 13]",
  "[N100 - 23]",
  "[N102 - 22]",
  "[N103 - 9]",
  "[N105 - 28]",
  "[N111 - 9]",
  "[N113 - 39]",
  "[N116 - 22]",
  "[N117 - 48]",
  "[N126 - 26]",
  "[N132 - 6]",
  "[N140 - 24]",
  "[N141 - 9]",
  "[N143 - 26]",
  "[N144 - 3]",
  "[N146 - 17]",
  "[N147 - 15]",
  "[N153 - 38]",
  "[N157 - 34]",
  "[N159 - 10]",
  "[N160 - 14]",
  "[N164 - 30]",
  "[N168 - 13]",
  "[N170 - 18]",
  "[N171 - 3]",
  "[N173 - 9]",
  "[N177 - 35]",
  "[N179 - 19]",
  "[N181 - 7]",
  "[N182 - 36]",
  "[N186 - 8]",
  "[N192 - 14]",
  "[N193 - 38]",
  "[N197 - 46]",
  "[N201 - 7]",
  "[N204 - 14]",
  "[N206 - 25]",
  "[N207 - 9]",
  "[N210 - 18]",
  "[N223 - 19]",
  "[N227 - 7]",
  "[N232 - 11]",
  "[N234 - 48]",
  "[N252 - 0]",
  "[N264 - 2]",
  "[N265 - 4]",
  "[N281 - 7]",
  "[N283 - 40]",
  "[N287 - 25]",
  "[N288 - 50]",
  "[N289 - 43]",
  "[N292 - 14]",
  "[N294 - 31]",
  "[N307 - 27]",
  "[N315 - 10]",
  "[N318 - 34]",
  "[N320 - 46]",
  "[N328 - 12]",
  "[N336 - 14]",
  "[N341 - 48]",
  "[N343 - 4]",
  "[N346 - 2]",
  "[N347 - 12]",
  "[N354 - 40]",
  "[N359 - 3]",
  "[N362 - 36]",
  "[N363 - 29]",
  "[N365 - 41]",
  "[N372 - 38]",
  "[N384 - 11]",
  "[N386 - 22]",
  "[N394 - 1]",
  "[N402 - 33]",
  "[N409 - 14]",
  "[N413 - 19]",
  "[N414 - 17]",
  "[N415 - 32]",
  "[N421 - 25]",
  "[N446 - 13]",
  "[N455 - 10]",
  "[N465 - 5]",
  "[N469 - 14]",
  "[N505 - 12]",
  "[N528 - 20]",
  "[N531 - 5]",
  "[N562 - 32]",
  "[N566 - 23]",
  "[N574 - 29]",
  "[N575 - 15]",
  "[N577 - 30]",
  "[N578 - 44]",
  "[N584 - 44]",
  "[N588 - 31]",
  "[N614 - 40]",
  "[N631 - 46]",
  "[N636 - 31]",
  "[N640 - 10]",
  "[N656 - 9]",
  "[N673 - 46]",
  "[N683 - 38]",
  "[N686 - 44]",
  "[N692 - 29]",
  "[N695 - 15]",
  "[N709 - 23]",
  "[N718 - 33]",
  "[N725 - 48]",
  "[N727 - 17]",
  "[N730 - 44]",
  "[N745 - 12]",
  "[N769 - 49]",
  "[N772 - 24]",
  "[N788 - 33]",
  "[N804 - 49]",
  "[N819 - 16]",
  "[N827 - 39]",
  "[N829 - 9]",
  "[N831 - 5]",
  "[N842 - 37]",
  "[N892 - 2]",
  "[N911 - 38]",
  "[N931 - 25]",
  "[N939 - 20]",
  "[N1010 - 40]"
 ],
 "height": 9,
 "max_symbol_size": 50,
 "opt_value": null,
 "opt_tiles_m1": [],
 "symbols_on_m1": [],
 "opt_tiles_m2": [],
 "symbols_on_m2": [],
 "seed": 1574015469.6911619
}